{"web":
    {"client_id":"358581589698-lt50hu0vaj1eq6o34si2duur7e9c915b.apps.googleusercontent.com",
        "project_id":"total-array-339322","auth_uri":"https://accounts.google.com/o/oauth2/auth",
        "token_uri":"https://oauth2.googleapis.com/token",
        "auth_provider_x509_cert_url":"https://www.googleapis.com/oauth2/v1/certs",
        "client_secret":"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",
        "redirect_uris":["http://localhost/drive/index.php"],"javascript_origins":["http://localhost"]}}